djehuty/__init__.py
djehuty/ui.py
djehuty/backup/database.py
djehuty/backup/figshare.py
djehuty/backup/ui.py
djehuty/backup/resources/contributors_organizations.json
djehuty/backup/resources/dois.json
djehuty/backup/resources/languages.json
djehuty/backup/resources/licenses.json
djehuty/backup/resources/public_collections.json
djehuty/backup/resources/root_categories.json
djehuty/utils/constants.py
djehuty/utils/convenience.py
djehuty/utils/rdf.py
djehuty/web/cache.py
djehuty/web/config.py
djehuty/web/database.py
djehuty/web/email_handler.py
djehuty/web/formatter.py
djehuty/web/locks.py
djehuty/web/s3.py
djehuty/web/ui.py
djehuty/web/validator.py
djehuty/web/wsgi.py
djehuty/web/xml_formatter.py
djehuty/web/zipfly.py
djehuty/web/resources/html_templates/400.html
djehuty/web/resources/html_templates/403.html
djehuty/web/resources/html_templates/404.html
djehuty/web/resources/html_templates/410.html
djehuty/web/resources/html_templates/500.html
djehuty/web/resources/html_templates/502.html
djehuty/web/resources/html_templates/activate_2fa_session.html
djehuty/web/resources/html_templates/author.html
djehuty/web/resources/html_templates/badge.svg
djehuty/web/resources/html_templates/categories.html
djehuty/web/resources/html_templates/category.html
djehuty/web/resources/html_templates/collection.html
djehuty/web/resources/html_templates/colors.css
djehuty/web/resources/html_templates/dataset.html
djehuty/web/resources/html_templates/dataset_access_request.html
djehuty/web/resources/html_templates/feedback.html
djehuty/web/resources/html_templates/git_instructions.html
djehuty/web/resources/html_templates/institutions.html
djehuty/web/resources/html_templates/jsonld.html
djehuty/web/resources/html_templates/layout.html
djehuty/web/resources/html_templates/loader.svg
djehuty/web/resources/html_templates/maintenance.html
djehuty/web/resources/html_templates/opendap_to_doi.html
djehuty/web/resources/html_templates/portal.html
djehuty-25.6.dist-info/licenses/LICENSE
djehuty-25.6.dist-info/METADATA
djehuty-25.6.dist-info/WHEEL
djehuty-25.6.dist-info/entry_points.txt
djehuty-25.6.dist-info/top_level.txt
djehuty-25.6.dist-info/RECORD
