Metadata-Version: 2.4
Name: djehuty
Version: 25.6
Summary: The 4TU.ResearchData and Nikhef data repository system
Author-email: Roel Janssen <r.r.e.janssen@tudelft.nl>
Project-URL: Homepage, https://data.4tu.nl/
Project-URL: Source Code, https://github.com/4TUResearchData/djehuty
Project-URL: Bug Tracker, https://github.com/4TUResearchData/djehuty/issues
Classifier: Programming Language :: Python :: 3
Classifier: Environment :: Web Environment
Classifier: License :: OSI Approved :: GNU Affero General Public License v3 or later (AGPLv3+)
Classifier: Operating System :: OS Independent
Requires-Python: >=3.9
License-File: LICENSE
Dynamic: license-file
